DAPPkg/Manager.py
DAPPkg/__init__.py
DAPPkg-0.0.1.dist-info/METADATA
DAPPkg-0.0.1.dist-info/WHEEL
DAPPkg-0.0.1.dist-info/top_level.txt
DAPPkg-0.0.1.dist-info/RECORD
