Metadata-Version: 2.1
Name: DAPPkg
Version: 0.0.1
Summary: Data Analysis Platform package
Home-page: 
Author: ksr8308
Author-email: 
Keywords: Data Analysis Platform,DAP,data analysis
Classifier: Programming Language :: Python :: 3.9
Classifier: Programming Language :: Python :: 3.10
Classifier: Programming Language :: Python :: 3.11
Requires-Python: >=3.9
Requires-Dist: numpy
Requires-Dist: pandas
Requires-Dist: scikit-learn
Requires-Dist: scipy
Requires-Dist: statsmodels
Requires-Dist: requests
